<mxfile host="app.diagrams.net" modified="2020-07-18T13:11:05.074Z" agent="5.0 (Windows NT 10.0; Win64; x64) AppleWebKit/537.36 (KHTML, like Gecko) Chrome/83.0.4103.116 Safari/537.36 Edg/83.0.478.64" etag="MIoBd_xYEbZfy3ZJLxWI" version="13.4.6" type="github">
  <diagram name="Page-1" id="dd472eb7-4b8b-5cd9-a60b-b15522922e76">
    <mxGraphModel dx="2031" dy="1089" grid="1" gridSize="10" guides="1" tooltips="1" connect="1" arrows="1" fold="1" page="1" pageScale="1" pageWidth="1100" pageHeight="850" background="#ffffff" math="0" shadow="0">
      <root>
        <mxCell id="0" />
        <mxCell id="1" parent="0" />
        <mxCell id="374e34682ed331ee-1" value="API/GATEWAY" style="ellipse;whiteSpace=wrap;html=1;rounded=0;shadow=0;dashed=0;comic=0;fontFamily=Verdana;fontSize=22;fontColor=#0069D1;fillColor=#f5f5f5;strokeColor=#666666;aspect=fixed;" parent="1" vertex="1">
          <mxGeometry x="408.5" y="275" width="243" height="243" as="geometry" />
        </mxCell>
        <mxCell id="l-dD7AaTVBmWllS7YnV5-1" style="edgeStyle=orthogonalEdgeStyle;rounded=0;orthogonalLoop=1;jettySize=auto;html=1;entryX=0.5;entryY=0;entryDx=0;entryDy=0;startArrow=block;startFill=1;" edge="1" parent="1" source="45236fa5f4b8e91a-1" target="374e34682ed331ee-1">
          <mxGeometry relative="1" as="geometry" />
        </mxCell>
        <mxCell id="l-dD7AaTVBmWllS7YnV5-25" style="edgeStyle=orthogonalEdgeStyle;rounded=0;orthogonalLoop=1;jettySize=auto;html=1;entryX=0.5;entryY=1;entryDx=0;entryDy=0;startArrow=block;startFill=1;" edge="1" parent="1" source="45236fa5f4b8e91a-1" target="l-dD7AaTVBmWllS7YnV5-17">
          <mxGeometry relative="1" as="geometry" />
        </mxCell>
        <mxCell id="45236fa5f4b8e91a-1" value="service-1" style="ellipse;whiteSpace=wrap;html=1;rounded=0;shadow=0;dashed=0;comic=0;fontFamily=Verdana;fontSize=22;fontColor=#0069D1;fillColor=#f5f5f5;strokeColor=#666666;" parent="1" vertex="1">
          <mxGeometry x="450" y="100" width="160" height="160" as="geometry" />
        </mxCell>
        <mxCell id="l-dD7AaTVBmWllS7YnV5-6" style="edgeStyle=orthogonalEdgeStyle;rounded=0;orthogonalLoop=1;jettySize=auto;html=1;startArrow=block;startFill=1;entryX=0.5;entryY=1;entryDx=0;entryDy=0;" edge="1" parent="1" source="45236fa5f4b8e91a-2" target="374e34682ed331ee-1">
          <mxGeometry relative="1" as="geometry">
            <mxPoint x="530" y="530" as="targetPoint" />
          </mxGeometry>
        </mxCell>
        <mxCell id="l-dD7AaTVBmWllS7YnV5-21" style="edgeStyle=orthogonalEdgeStyle;rounded=0;orthogonalLoop=1;jettySize=auto;html=1;exitX=0.5;exitY=1;exitDx=0;exitDy=0;entryX=0.5;entryY=0;entryDx=0;entryDy=0;startArrow=block;startFill=1;" edge="1" parent="1" source="45236fa5f4b8e91a-2" target="l-dD7AaTVBmWllS7YnV5-10">
          <mxGeometry relative="1" as="geometry" />
        </mxCell>
        <mxCell id="45236fa5f4b8e91a-2" value="service-5&lt;br&gt;" style="ellipse;whiteSpace=wrap;html=1;rounded=0;shadow=0;dashed=0;comic=0;fontFamily=Verdana;fontSize=22;fontColor=#0069D1;fillColor=#f5f5f5;strokeColor=#666666;" parent="1" vertex="1">
          <mxGeometry x="450" y="590" width="160" height="160" as="geometry" />
        </mxCell>
        <mxCell id="l-dD7AaTVBmWllS7YnV5-4" style="edgeStyle=orthogonalEdgeStyle;rounded=0;orthogonalLoop=1;jettySize=auto;html=1;entryX=1;entryY=0.5;entryDx=0;entryDy=0;startArrow=block;startFill=1;" edge="1" parent="1" source="45236fa5f4b8e91a-3" target="374e34682ed331ee-1">
          <mxGeometry relative="1" as="geometry" />
        </mxCell>
        <mxCell id="l-dD7AaTVBmWllS7YnV5-23" style="edgeStyle=orthogonalEdgeStyle;rounded=0;orthogonalLoop=1;jettySize=auto;html=1;entryX=0.5;entryY=0;entryDx=0;entryDy=0;startArrow=block;startFill=1;" edge="1" parent="1" source="45236fa5f4b8e91a-3" target="l-dD7AaTVBmWllS7YnV5-15">
          <mxGeometry relative="1" as="geometry" />
        </mxCell>
        <mxCell id="45236fa5f4b8e91a-3" value="service-3" style="ellipse;whiteSpace=wrap;html=1;rounded=0;shadow=0;dashed=0;comic=0;fontFamily=Verdana;fontSize=22;fontColor=#0069D1;fillColor=#f5f5f5;strokeColor=#666666;" parent="1" vertex="1">
          <mxGeometry x="770" y="345" width="160" height="160" as="geometry" />
        </mxCell>
        <mxCell id="l-dD7AaTVBmWllS7YnV5-8" style="edgeStyle=orthogonalEdgeStyle;rounded=0;orthogonalLoop=1;jettySize=auto;html=1;entryX=0;entryY=0.5;entryDx=0;entryDy=0;startArrow=block;startFill=1;" edge="1" parent="1" source="45236fa5f4b8e91a-4" target="374e34682ed331ee-1">
          <mxGeometry relative="1" as="geometry" />
        </mxCell>
        <mxCell id="l-dD7AaTVBmWllS7YnV5-19" style="edgeStyle=orthogonalEdgeStyle;rounded=0;orthogonalLoop=1;jettySize=auto;html=1;exitX=0;exitY=0.5;exitDx=0;exitDy=0;entryX=0.5;entryY=1;entryDx=0;entryDy=0;startArrow=block;startFill=1;" edge="1" parent="1" source="45236fa5f4b8e91a-4" target="l-dD7AaTVBmWllS7YnV5-12">
          <mxGeometry relative="1" as="geometry" />
        </mxCell>
        <mxCell id="45236fa5f4b8e91a-4" value="service-7" style="ellipse;whiteSpace=wrap;html=1;rounded=0;shadow=0;dashed=0;comic=0;fontFamily=Verdana;fontSize=22;fontColor=#0069D1;fillColor=#f5f5f5;strokeColor=#666666;" parent="1" vertex="1">
          <mxGeometry x="130" y="345" width="160" height="160" as="geometry" />
        </mxCell>
        <mxCell id="l-dD7AaTVBmWllS7YnV5-9" style="edgeStyle=orthogonalEdgeStyle;rounded=0;orthogonalLoop=1;jettySize=auto;html=1;entryX=0;entryY=0;entryDx=0;entryDy=0;startArrow=block;startFill=1;" edge="1" parent="1" source="45236fa5f4b8e91a-5" target="374e34682ed331ee-1">
          <mxGeometry relative="1" as="geometry" />
        </mxCell>
        <mxCell id="l-dD7AaTVBmWllS7YnV5-18" style="edgeStyle=orthogonalEdgeStyle;rounded=0;orthogonalLoop=1;jettySize=auto;html=1;entryX=0.5;entryY=1;entryDx=0;entryDy=0;startArrow=block;startFill=1;" edge="1" parent="1" source="45236fa5f4b8e91a-5" target="l-dD7AaTVBmWllS7YnV5-13">
          <mxGeometry relative="1" as="geometry" />
        </mxCell>
        <mxCell id="45236fa5f4b8e91a-5" value="service-n" style="ellipse;whiteSpace=wrap;html=1;rounded=0;shadow=0;dashed=0;comic=0;fontFamily=Verdana;fontSize=22;fontColor=#0069D1;fillColor=#f5f5f5;strokeColor=#666666;" parent="1" vertex="1">
          <mxGeometry x="210" y="115" width="160" height="160" as="geometry" />
        </mxCell>
        <mxCell id="l-dD7AaTVBmWllS7YnV5-3" style="edgeStyle=orthogonalEdgeStyle;rounded=0;orthogonalLoop=1;jettySize=auto;html=1;exitX=0;exitY=1;exitDx=0;exitDy=0;entryX=1;entryY=0;entryDx=0;entryDy=0;startArrow=block;startFill=1;" edge="1" parent="1" source="45236fa5f4b8e91a-6" target="374e34682ed331ee-1">
          <mxGeometry relative="1" as="geometry" />
        </mxCell>
        <mxCell id="l-dD7AaTVBmWllS7YnV5-24" style="edgeStyle=orthogonalEdgeStyle;rounded=0;orthogonalLoop=1;jettySize=auto;html=1;entryX=0.5;entryY=1;entryDx=0;entryDy=0;startArrow=block;startFill=1;" edge="1" parent="1" source="45236fa5f4b8e91a-6" target="l-dD7AaTVBmWllS7YnV5-14">
          <mxGeometry relative="1" as="geometry" />
        </mxCell>
        <mxCell id="45236fa5f4b8e91a-6" value="service-2" style="ellipse;whiteSpace=wrap;html=1;rounded=0;shadow=0;dashed=0;comic=0;fontFamily=Verdana;fontSize=22;fontColor=#0069D1;fillColor=#f5f5f5;strokeColor=#666666;" parent="1" vertex="1">
          <mxGeometry x="690" y="90" width="160" height="160" as="geometry" />
        </mxCell>
        <mxCell id="l-dD7AaTVBmWllS7YnV5-5" style="edgeStyle=orthogonalEdgeStyle;rounded=0;orthogonalLoop=1;jettySize=auto;html=1;entryX=1;entryY=1;entryDx=0;entryDy=0;startArrow=block;startFill=1;" edge="1" parent="1" source="45236fa5f4b8e91a-7" target="374e34682ed331ee-1">
          <mxGeometry relative="1" as="geometry" />
        </mxCell>
        <mxCell id="l-dD7AaTVBmWllS7YnV5-22" style="edgeStyle=orthogonalEdgeStyle;rounded=0;orthogonalLoop=1;jettySize=auto;html=1;entryX=0.5;entryY=0;entryDx=0;entryDy=0;startArrow=block;startFill=1;" edge="1" parent="1" source="45236fa5f4b8e91a-7" target="l-dD7AaTVBmWllS7YnV5-16">
          <mxGeometry relative="1" as="geometry" />
        </mxCell>
        <mxCell id="45236fa5f4b8e91a-7" value="service-4" style="ellipse;whiteSpace=wrap;html=1;rounded=0;shadow=0;dashed=0;comic=0;fontFamily=Verdana;fontSize=22;fontColor=#0069D1;fillColor=#f5f5f5;strokeColor=#666666;" parent="1" vertex="1">
          <mxGeometry x="720" y="570" width="160" height="160" as="geometry" />
        </mxCell>
        <mxCell id="l-dD7AaTVBmWllS7YnV5-7" style="edgeStyle=orthogonalEdgeStyle;rounded=0;orthogonalLoop=1;jettySize=auto;html=1;entryX=0;entryY=1;entryDx=0;entryDy=0;startArrow=block;startFill=1;" edge="1" parent="1" source="45236fa5f4b8e91a-8" target="374e34682ed331ee-1">
          <mxGeometry relative="1" as="geometry" />
        </mxCell>
        <mxCell id="l-dD7AaTVBmWllS7YnV5-20" style="edgeStyle=orthogonalEdgeStyle;rounded=0;orthogonalLoop=1;jettySize=auto;html=1;entryX=0.5;entryY=1;entryDx=0;entryDy=0;startArrow=block;startFill=1;" edge="1" parent="1" source="45236fa5f4b8e91a-8" target="l-dD7AaTVBmWllS7YnV5-11">
          <mxGeometry relative="1" as="geometry" />
        </mxCell>
        <mxCell id="45236fa5f4b8e91a-8" value="service-6" style="ellipse;whiteSpace=wrap;html=1;rounded=0;shadow=0;dashed=0;comic=0;fontFamily=Verdana;fontSize=22;fontColor=#0069D1;fillColor=#f5f5f5;strokeColor=#666666;" parent="1" vertex="1">
          <mxGeometry x="200" y="560" width="160" height="160" as="geometry" />
        </mxCell>
        <mxCell id="l-dD7AaTVBmWllS7YnV5-10" value="" style="shape=cylinder;whiteSpace=wrap;html=1;boundedLbl=1;backgroundOutline=1;" vertex="1" parent="1">
          <mxGeometry x="651.5" y="740" width="60" height="80" as="geometry" />
        </mxCell>
        <mxCell id="l-dD7AaTVBmWllS7YnV5-11" value="" style="shape=cylinder;whiteSpace=wrap;html=1;boundedLbl=1;backgroundOutline=1;" vertex="1" parent="1">
          <mxGeometry x="60" y="650" width="60" height="80" as="geometry" />
        </mxCell>
        <mxCell id="l-dD7AaTVBmWllS7YnV5-12" value="" style="shape=cylinder;whiteSpace=wrap;html=1;boundedLbl=1;backgroundOutline=1;" vertex="1" parent="1">
          <mxGeometry x="20" y="370" width="60" height="80" as="geometry" />
        </mxCell>
        <mxCell id="l-dD7AaTVBmWllS7YnV5-13" value="" style="shape=cylinder;whiteSpace=wrap;html=1;boundedLbl=1;backgroundOutline=1;" vertex="1" parent="1">
          <mxGeometry x="100" y="80" width="60" height="80" as="geometry" />
        </mxCell>
        <mxCell id="l-dD7AaTVBmWllS7YnV5-14" value="" style="shape=cylinder;whiteSpace=wrap;html=1;boundedLbl=1;backgroundOutline=1;" vertex="1" parent="1">
          <mxGeometry x="940" y="100" width="60" height="80" as="geometry" />
        </mxCell>
        <mxCell id="l-dD7AaTVBmWllS7YnV5-15" value="" style="shape=cylinder;whiteSpace=wrap;html=1;boundedLbl=1;backgroundOutline=1;" vertex="1" parent="1">
          <mxGeometry x="1010" y="380" width="60" height="80" as="geometry" />
        </mxCell>
        <mxCell id="l-dD7AaTVBmWllS7YnV5-16" value="" style="shape=cylinder;whiteSpace=wrap;html=1;boundedLbl=1;backgroundOutline=1;" vertex="1" parent="1">
          <mxGeometry x="910" y="710" width="60" height="80" as="geometry" />
        </mxCell>
        <mxCell id="l-dD7AaTVBmWllS7YnV5-17" value="" style="shape=cylinder;whiteSpace=wrap;html=1;boundedLbl=1;backgroundOutline=1;" vertex="1" parent="1">
          <mxGeometry x="408.5" y="10" width="60" height="80" as="geometry" />
        </mxCell>
      </root>
    </mxGraphModel>
  </diagram>
</mxfile>
